tree_sitter_clingo/__init__.py
tree_sitter_clingo/__init__.pyi
tree_sitter_clingo/_binding.pyd
tree_sitter_clingo/binding.c
tree_sitter_clingo/py.typed
tree_sitter_clingo/queries/highlights.scm
tree_sitter_clingo/queries/indents.scm
tree_sitter_clingo/queries/injections.scm
tree_sitter_clingo/queries/textobjects.scm
tree_sitter_clingo-1.0.4.dist-info/licenses/LICENSE
tree_sitter_clingo-1.0.4.dist-info/METADATA
tree_sitter_clingo-1.0.4.dist-info/WHEEL
tree_sitter_clingo-1.0.4.dist-info/top_level.txt
tree_sitter_clingo-1.0.4.dist-info/RECORD
