Metadata-Version: 2.4
Name: tree-sitter-clingo
Version: 1.0.4
Summary: Clingo grammar for tree-sitter
Author: Roland Kaminski, Sven Thiele
License: MIT
Project-URL: Homepage, https://github.com/potassco/tree-sitter-clingo
Keywords: incremental,parsing,tree-sitter,clingo
Classifier: Intended Audience :: Developers
Classifier: Topic :: Software Development :: Compilers
Classifier: Topic :: Text Processing :: Linguistic
Classifier: Typing :: Typed
Requires-Python: >=3.10
License-File: LICENSE
Provides-Extra: core
Requires-Dist: tree-sitter~=0.25; extra == "core"
Dynamic: license-file
